async_riot_api/__init__.py
async_riot_api/api.py
async_riot_api/types/__init__.py
async_riot_api-0.0.43.dist-info/METADATA
async_riot_api-0.0.43.dist-info/WHEEL
async_riot_api-0.0.43.dist-info/top_level.txt
async_riot_api-0.0.43.dist-info/RECORD
