Metadata-Version: 2.1
Name: async-riot-api
Version: 0.0.43
Summary: Async wrapper for the Riot Games API for League of Legends
Home-page: https://async-riot-api.readthedocs.io/en/latest/
Author: Andrea Princic
Author-email: princic.1837592@studenti.uniroma1.it
Requires-Python: >=3.7
Requires-Dist: aiohttp
Requires-Dist: requests
Requires-Dist: fuzzywuzzy
Requires-Dist: python-Levenshtein
